Metadata-Version: 2.1
Name: hellotome
Version: 2.0
Summary: Package to get a personalized greeting
Home-page: https://github.com/vinzegtz/hellotome
Author: Vicente Gutiérrez
Author-email: vinzegtz@gmail.com
License: UNKNOWN
Download-URL: https://github.com/vinzegtz/hellotome/archive/v2.0.tar.gz
Keywords: hello-world,hello,greeting
Platform: UNKNOWN
Classifier: Intended Audience :: Developers
Classifier: Topic :: Education
Classifier: License :: OSI Approved :: MIT License
Classifier: Programming Language :: Python :: 3
